LICENSE
README.md
setup.py
archctl/__init__.py
archctl/__main__.py
archctl/cli.py
archctl/inquirer.py
archctl/logger.py
archctl/main.py
archctl/validation.py
archctl.egg-info/PKG-INFO
archctl.egg-info/SOURCES.txt
archctl.egg-info/dependency_links.txt
archctl.egg-info/entry_points.txt
archctl.egg-info/not-zip-safe
archctl.egg-info/requires.txt
archctl.egg-info/top_level.txt