Metadata-Version: 2.1
Name: archctl
Version: 0.1.1
Summary: A command-line utility that wraps the use of cookiecutter andmanages both Templates and Projects GitHub Repositories
Home-page: https://github.com/archctl/archctl
Author: Adrian Garcia
Author-email: adriangarciasb@outlook.com
License: GPL-3.0
Keywords: archctl,Python,projects,project templates,project directory,package,packaging
Classifier: Development Status :: 2 - Pre-Alpha
Classifier: Environment :: Console
Classifier: Intended Audience :: Developers
Classifier: Natural Language :: English
Classifier: License :: OSI Approved :: GNU General Public License v3 (GPLv3)
Classifier: Programming Language :: Python :: 3
Classifier: Programming Language :: Python
Classifier: Topic :: Software Development
Requires-Python: >=3.7
License-File: LICENSE
